jatool/__init__.py
jatool/fiction_info_new.txt
jatool/function.py
jatool/stopwords_list_new.txt
jatool-1.992.dist-info/METADATA
jatool-1.992.dist-info/WHEEL
jatool-1.992.dist-info/top_level.txt
jatool-1.992.dist-info/RECORD
