Metadata-Version: 2.1
Name: jatool
Version: 1.992
Summary: A Python package for jatools
Home-page: https://github.com/bigbrolv/jatool
Author: Pigpig
Author-email: 21310238@tongji.edu.cn
Classifier: Programming Language :: Python :: 3
Classifier: License :: OSI Approved :: MIT License
Classifier: Operating System :: OS Independent
Requires-Dist: pandas
Requires-Dist: ginza
Requires-Dist: chardet
Requires-Dist: ja-ginza
Requires-Dist: gensim
Requires-Dist: matplotlib
Requires-Dist: scikit-learn
Requires-Dist: seaborn
Requires-Dist: transformers
Requires-Dist: torch
Requires-Dist: tensorflow
Requires-Dist: xformers
Requires-Dist: fugashi
Requires-Dist: ipadic
